main.py
setup.py
HabitMF.egg-info/PKG-INFO
HabitMF.egg-info/SOURCES.txt
HabitMF.egg-info/dependency_links.txt
HabitMF.egg-info/requires.txt
HabitMF.egg-info/top_level.txt